poseidon/__init__.py
poseidon/poseidon.py
poseidon_enos_api-0.0.1.dist-info/METADATA
poseidon_enos_api-0.0.1.dist-info/WHEEL
poseidon_enos_api-0.0.1.dist-info/top_level.txt
poseidon_enos_api-0.0.1.dist-info/RECORD
